COMTool/Combobox.py
COMTool/Main.py
COMTool/__init__.py
COMTool/autoUpdate.py
COMTool/helpAbout.py
COMTool/i18n.py
COMTool/logger.py
COMTool/main2.py
COMTool/parameters.py
COMTool/pluginItems.py
COMTool/qta_icon_browser.py
COMTool/settings.py
COMTool/test.py
COMTool/utils.py
COMTool/utils_ui.py
COMTool/version.py
COMTool/wave.py
COMTool/widgets.py
COMTool/win32_utils.py
COMTool/assets/RaspberryPiScreenshot.png
COMTool/assets/arrow-down.png
COMTool/assets/arrow-left-white.png
COMTool/assets/arrow-left.png
COMTool/assets/arrow-right-white.png
COMTool/assets/arrow-right.png
COMTool/assets/close.png
COMTool/assets/donate_alipay.jpg
COMTool/assets/donate_wechat.jpg
COMTool/assets/help-white.png
COMTool/assets/help.png
COMTool/assets/left.png
COMTool/assets/logo.icns
COMTool/assets/logo.ico
COMTool/assets/logo.png
COMTool/assets/logo2.png
COMTool/assets/right.png
COMTool/assets/screenshot_V1.0.png
COMTool/assets/screenshot_V1.3.png
COMTool/assets/screenshot_V1.4_night.png
COMTool/assets/screenshot_V1.7.png
COMTool/assets/screenshot_graph.png
COMTool/assets/screenshot_macos.jpg
COMTool/assets/screenshot_protocol_v2.3.png
COMTool/assets/screenshot_terminal.png
COMTool/assets/screenshot_v2.png
COMTool/assets/screenshot_v2_white.png
COMTool/assets/skin-white.png
COMTool/assets/skin.png
COMTool/assets/tcp_udp.png
COMTool/assets/wave-white.png
COMTool/assets/wave.png
COMTool/assets/qss/style-dark.qss
COMTool/assets/qss/style.qss
COMTool/conn/__init__.py
COMTool/conn/base.py
COMTool/conn/conn_serial.py
COMTool/conn/conn_ssh.py
COMTool/conn/conn_tcp_udp.py
COMTool/conn/test_tcp_udp.py
COMTool/locales/en/LC_MESSAGES/messages.mo
COMTool/locales/en/LC_MESSAGES/messages.po
COMTool/locales/ja/LC_MESSAGES/messages.mo
COMTool/locales/ja/LC_MESSAGES/messages.po
COMTool/locales/zh_CN/LC_MESSAGES/messages.mo
COMTool/locales/zh_CN/LC_MESSAGES/messages.po
COMTool/locales/zh_TW/LC_MESSAGES/messages.mo
COMTool/locales/zh_TW/LC_MESSAGES/messages.po
COMTool/plugins/__init__.py
COMTool-3.2.1.dist-info/LICENSE
COMTool-3.2.1.dist-info/METADATA
COMTool-3.2.1.dist-info/WHEEL
COMTool-3.2.1.dist-info/entry_points.txt
COMTool-3.2.1.dist-info/top_level.txt
COMTool-3.2.1.dist-info/RECORD
