Metadata-Version: 2.1
Name: COMTool
Version: 3.2.1
Summary: Cross platform serial debug assistant with GUI
Home-page: https://github.com/Neutree/COMTool
Author: Neucrack
Author-email: czd666666@gmail.com
License: LGPL-3.0
Keywords: Serial Debug Tool Assistant
Platform: UNKNOWN
Classifier: Development Status :: 5 - Production/Stable
Classifier: Intended Audience :: Developers
Classifier: Topic :: Software Development :: Embedded Systems
Classifier: Topic :: Software Development :: Debuggers
Classifier: License :: OSI Approved :: GNU Lesser General Public License v3 (LGPLv3)
Classifier: Programming Language :: Python :: 3
Classifier: Programming Language :: Python :: 3.8
Classifier: Programming Language :: Python :: 3.9
Classifier: Programming Language :: Python :: 3.10
License-File: LICENSE
Requires-Dist: Babel
Requires-Dist: coloredlogs
Requires-Dist: paramiko
Requires-Dist: pyperclip
Requires-Dist: pyqt5 (>=5)
Requires-Dist: pyqtgraph
Requires-Dist: pyserial (>=3.4)
Requires-Dist: pyte
Requires-Dist: qtawesome (>=1.1.1)
Requires-Dist: requests
